pysimhash.so
pysimhash-1.0.6.dist-info/METADATA
pysimhash-1.0.6.dist-info/RECORD
pysimhash-1.0.6.dist-info/WHEEL
pysimhash-1.0.6.dist-info/top_level.txt
