Metadata-Version: 2.1
Name: pysimhash
Version: 1.0.6
Summary: a simhash module in cpp for python
Home-page: https://github.com/skiloop/simhash
Author: Skiloop
Author-email: skiloop@gmail.com
License: MIT
Platform: UNKNOWN
Requires: six
